python_poker/__init__.py
python_poker-0.0.1.dist-info/LICENSE
python_poker-0.0.1.dist-info/METADATA
python_poker-0.0.1.dist-info/WHEEL
python_poker-0.0.1.dist-info/RECORD
